{
    "name": "component_physical-exams",
    "uuid": "xxxx",
    "processor": "EncounterFormProcessor",
    "pages": [
        {
            "label": "Physical Exams",
            "sections": [
                {
                    "label": "Physical Exams",
                    "questions": [
                        {
                            "label": "General exam:",
                            "questionOptions": {
                                "concept": "a899eb24-1350-11df-a1f1-0026b9348838",
                                "answers": [
                                    {
                                        "concept": "a899e7b4-1350-11df-a1f1-0026b9348838",
                                        "label": "Normal"
                                    },
                                    {
                                        "concept": "a8a6ce8e-1350-11df-a1f1-0026b9348838",
                                        "label": "Temporal wasting"
                                    }
                                ],
                                "rendering": "select"
                            },
                            "type": "obs",
                            "validators": []
                        },
                        {
                            "label": "Skin :",
                            "questionOptions": {
                                "concept": "a899ec00-1350-11df-a1f1-0026b9348838",
                                "answers": [
                                    {
                                        "concept": "a899e7b4-1350-11df-a1f1-0026b9348838",
                                        "label": "Normal"
                                    },
                                    {
                                        "concept": "a8957184-1350-11df-a1f1-0026b9348838",
                                        "label": "Kaposis sacorma"
                                    },
                                    {
                                        "concept": "a895776a-1350-11df-a1f1-0026b9348838",
                                        "label": "Rash"
                                    }
                                ],
                                "rendering": "multiCheckbox"
                            },
                            "type": "obs",
                            "validators": []
                        },
                        {
                            "label": "Lymph nodes:",
                            "questionOptions": {
                                "concept": "a899ecdc-1350-11df-a1f1-0026b9348838",
                                "answers": [
                                    {
                                        "concept": "a899e7b4-1350-11df-a1f1-0026b9348838",
                                        "label": "Normal"
                                    },
                                    {
                                        "concept": "a8956d1a-1350-11df-a1f1-0026b9348838",
                                        "label": "Submandibular"
                                    },
                                    {
                                        "concept": "a89693e8-1350-11df-a1f1-0026b9348838",
                                        "label": "Cervical"
                                    },
                                    {
                                        "concept": "a895703a-1350-11df-a1f1-0026b9348838",
                                        "label": "Inguinal"
                                    },
                                    {
                                        "concept": "a8956ef0-1350-11df-a1f1-0026b9348838",
                                        "label": "Supraclavicular"
                                    },
                                    {
                                        "concept": "a8a67a60-1350-11df-a1f1-0026b9348838",
                                        "label": "Auxillary"
                                    }
                                ],
                                "rendering": "multiCheckbox"
                            },
                            "type": "obs",
                            "validators": []
                        },
                        {
                            "label": "Respiratory exam :",
                            "questionOptions": {
                                "concept": "a899eeb2-1350-11df-a1f1-0026b9348838",
                                "answers": [
                                    {
                                        "concept": "a899e7b4-1350-11df-a1f1-0026b9348838",
                                        "label": "Normal"
                                    },
                                    {
                                        "concept": "a899e890-1350-11df-a1f1-0026b9348838",
                                        "label": "Abnormal"
                                    }
                                ],
                                "rendering": "select"
                            },
                            "type": "obs",
                            "validators": []
                        },
                        {
                            "label": "HEENT:",
                            "questionOptions": {
                                "concept": "a899edcc-1350-11df-a1f1-0026b9348838",
                                "answers": [
                                    {
                                        "concept": "a899e7b4-1350-11df-a1f1-0026b9348838",
                                        "label": "Normal"
                                    },
                                    {
                                        "concept": "a8a6c704-1350-11df-a1f1-0026b9348838",
                                        "label": "Sclera icteric"
                                    },
                                    {
                                        "concept": "a8957ad0-1350-11df-a1f1-0026b9348838",
                                        "label": "Conjunctiva pale"
                                    },
                                    {
                                        "concept": "a8957c88-1350-11df-a1f1-0026b9348838",
                                        "label": "Fundal abnormality"
                                    },
                                    {
                                        "concept": "a8961af8-1350-11df-a1f1-0026b9348838",
                                        "label": "Cerumen impaction "
                                    },
                                    {
                                        "concept": "a898aea8-1350-11df-a1f1-0026b9348838",
                                        "label": "TM injected"
                                    },
                                    {
                                        "concept": "a8957846-1350-11df-a1f1-0026b9348838",
                                        "label": "Trachea deviated"
                                    },
                                    {
                                        "concept": "a8a6b476-1350-11df-a1f1-0026b9348838",
                                        "label": "Nuchal rigidity"
                                    },
                                    {
                                        "concept": "a8a8209a-1350-11df-a1f1-0026b9348838",
                                        "label": "Thrush"
                                    },
                                    {
                                        "concept": "a8969532-1350-11df-a1f1-0026b9348838",
                                        "label": "Kaposi sarcoma"
                                    },
                                    {
                                        "concept": "a890eb28-1350-11df-a1f1-0026b9348838",
                                        "label": "Significant dental caries"
                                    }
                                ],
                                "rendering": "multiCheckbox"
                            },
                            "type": "obs",
                            "validators": []
                        },
                        {
                            "label": "Cardiac exam:",
                            "questionOptions": {
                                "concept": "a899ef84-1350-11df-a1f1-0026b9348838",
                                "answers": [
                                    {
                                        "concept": "a899e7b4-1350-11df-a1f1-0026b9348838",
                                        "label": "Normal"
                                    },
                                    {
                                        "concept": "a8a6b11a-1350-11df-a1f1-0026b9348838",
                                        "label": "Systolic ejection murmur "
                                    },
                                    {
                                        "concept": "a8a6ada0-1350-11df-a1f1-0026b9348838",
                                        "label": "Holosystolic murmur"
                                    },
                                    {
                                        "concept": "a8a6abf2-1350-11df-a1f1-0026b9348838",
                                        "label": "Diastolic decrescendo"
                                    },
                                    {
                                        "concept": "a8a6af58-1350-11df-a1f1-0026b9348838",
                                        "label": "Diastolic rumble"
                                    },
                                    {
                                        "concept": "a8a6aa3a-1350-11df-a1f1-0026b9348838",
                                        "label": "Evidence for enlargement"
                                    },
                                    {
                                        "concept": "a8a6a814-1350-11df-a1f1-0026b9348838",
                                        "label": "LV lift"
                                    },
                                    {
                                        "concept": "a8a6a954-1350-11df-a1f1-0026b9348838",
                                        "label": "RV lift"
                                    },
                                    {
                                        "concept": "a8962bec-1350-11df-a1f1-0026b9348838",
                                        "label": "S3 gallop"
                                    },
                                    {
                                        "concept": "a8a6b980-1350-11df-a1f1-0026b9348838",
                                        "label": "Pericardial friction rub"
                                    }
                                ],
                                "rendering": "multiCheckbox"
                            },
                            "type": "obs",
                            "validators": []
                        },
                        {
                            "label": "Abdominal exam:",
                            "questionOptions": {
                                "concept": "a899f04c-1350-11df-a1f1-0026b9348838",
                                "answers": [
                                    {
                                        "concept": "a899e7b4-1350-11df-a1f1-0026b9348838",
                                        "label": "Normal"
                                    },
                                    {
                                        "concept": "a8a66e58-1350-11df-a1f1-0026b9348838",
                                        "label": "Tender to palpitation"
                                    },
                                    {
                                        "concept": "a896464a-1350-11df-a1f1-0026b9348838",
                                        "label": "Ascites"
                                    },
                                    {
                                        "concept": "a8a66ca0-1350-11df-a1f1-0026b9348838",
                                        "label": "Mass"
                                    },
                                    {
                                        "concept": "a8a4cd28-1350-11df-a1f1-0026b9348838",
                                        "label": "Hepatomegaly"
                                    },
                                    {
                                        "concept": "a8a4cdfa-1350-11df-a1f1-0026b9348838",
                                        "label": "Splenomegaly"
                                    }
                                ],
                                "rendering": "multiCheckbox"
                            },
                            "type": "obs",
                            "validators": []
                        },
                        {
                            "label": "Urogenital exam:",
                            "questionOptions": {
                                "concept": "a899f11e-1350-11df-a1f1-0026b9348838",
                                "answers": [
                                    {
                                        "concept": "a899e7b4-1350-11df-a1f1-0026b9348838",
                                        "label": "Normal"
                                    },
                                    {
                                        "concept": "a899e890-1350-11df-a1f1-0026b9348838",
                                        "label": "Abnormal"
                                    },
                                    {
                                        "concept": "a899ea48-1350-11df-a1f1-0026b9348838",
                                        "label": "Not done"
                                    }
                                ],
                                "rendering": "select"
                            },
                            "type": "obs",
                            "validators": []
                        },
                        {
                            "label": "Extremies exam:",
                            "questionOptions": {
                                "concept": "a899f1e6-1350-11df-a1f1-0026b9348838",
                                "answers": [
                                    {
                                        "concept": "a899e7b4-1350-11df-a1f1-0026b9348838",
                                        "label": "Normal"
                                    },
                                    {
                                        "concept": "a896537e-1350-11df-a1f1-0026b9348838",
                                        "label": "Edema"
                                    },
                                    {
                                        "concept": "a898b132-1350-11df-a1f1-0026b9348838",
                                        "label": "Leg ulcers"
                                    },
                                    {
                                        "concept": "a892e2ac-1350-11df-a1f1-0026b9348838",
                                        "label": "Cellulitis"
                                    },
                                    {
                                        "concept": "a8957184-1350-11df-a1f1-0026b9348838",
                                        "label": "Kaposis sarcoma"
                                    }
                                ],
                                "rendering": "multiCheckbox"
                            },
                            "type": "obs",
                            "validators": []
                        },
                        {
                            "label": "Musculoskeletal exam:",
                            "questionOptions": {
                                "concept": "a899f2ae-1350-11df-a1f1-0026b9348838",
                                "answers": [
                                    {
                                        "concept": "a899e7b4-1350-11df-a1f1-0026b9348838",
                                        "label": "Normal"
                                    },
                                    {
                                        "concept": "a899e890-1350-11df-a1f1-0026b9348838",
                                        "label": "Abnormal"
                                    }
                                ],
                                "rendering": "select"
                            },
                            "type": "obs",
                            "validators": []
                        },
                        {
                            "label": "Developmental exam:",
                            "id": "phyDevelopment",
                            "questionOptions": {
                                "concept": "a89b228c-1350-11df-a1f1-0026b9348838",
                                "answers": [
                                    {
                                        "concept": "a899e7b4-1350-11df-a1f1-0026b9348838",
                                        "label": "Normal"
                                    },
                                    {
                                        "concept": "a8ad48cc-1350-11df-a1f1-0026b9348838",
                                        "label": "Delayed milestones"
                                    },
                                    {
                                        "concept": "a8ad4b60-1350-11df-a1f1-0026b9348838",
                                        "label": "Regressed milestones"
                                    }
                                ],
                                "rendering": "multiCheckbox"
                            },
                            "type": "obs",
                            "validators": []
                        },
                        {
                            "label": "Neurologic exam:",
                            "questionOptions": {
                                "concept": "a899f380-1350-11df-a1f1-0026b9348838",
                                "answers": [
                                    {
                                        "concept": "a899e7b4-1350-11df-a1f1-0026b9348838",
                                        "label": "Normal"
                                    },
                                    {
                                        "concept": "a8965b30-1350-11df-a1f1-0026b9348838",
                                        "label": "Cranial nerve abnormality"
                                    },
                                    {
                                        "concept": "a89565ea-1350-11df-a1f1-0026b9348838",
                                        "label": "Decreased sensation lower extremies"
                                    },
                                    {
                                        "concept": "a8a676fa-1350-11df-a1f1-0026b9348838",
                                        "label": "Abnormal gait"
                                    },
                                    {
                                        "concept": "a8ad3a26-1350-11df-a1f1-0026b9348838",
                                        "label": "Focal weakness"
                                    }
                                ],
                                "rendering": "multiCheckbox"
                            },
                            "type": "obs",
                            "validators": []
                        },
                        {
                            "label": "Psychiatric exam:",
                            "questionOptions": {
                                "concept": "a899f452-1350-11df-a1f1-0026b9348838",
                                "answers": [
                                    {
                                        "concept": "a899e7b4-1350-11df-a1f1-0026b9348838",
                                        "label": "Normal"
                                    },
                                    {
                                        "concept": "a8935fde-1350-11df-a1f1-0026b9348838",
                                        "label": "Depressed"
                                    },
                                    {
                                        "concept": "a8a68e7e-1350-11df-a1f1-0026b9348838",
                                        "label": "Dementia"
                                    },
                                    {
                                        "concept": "a8ad3b02-1350-11df-a1f1-0026b9348838",
                                        "label": "Confused"
                                    }
                                ],
                                "rendering": "multiCheckbox"
                            },
                            "type": "obs",
                            "validators": []
                        }
                    ]
                },
                {
                    "label": "Physical Exams, Notes",
                    "isExpanded": "true",
                    "questions": [
                        {
                            "label": "Physical exams, notes:",
                            "type": "obs",
                            "id": "phyText",
                            "questionOptions": {
                                "concept": "a8a0cc32-1350-11df-a1f1-0026b9348838",
                                "rendering": "textarea",
                                "rows": 15
                            }
                        }
                    ]
                }
            ]
        }
    ],
    "version": "0.01",
    "published": true,
    "retired": false,
    "encounter": "ACTGADULTRETURN"
}